<Alloy>
	<TableViewRow class="container" hasChild="false" touchEnabled="false" selectionStyle="Ti.UI.iPhone.TableViewCellSelectionStyle.NONE">
		<View id="contents" layout="vertical" touchEnabled="false">
			<View class="fragment" layout="horizontal">
				<Label class="heading">Order Status:</Label>
				<Label id="statusLabel">New</Label>
			</View>
			<View class="fragment bottomFragment">
				<ImageView image="/images/statusbar-40px.png" top="10dp"></ImageView>
			</View>
		</View>
	</TableViewRow>
</Alloy>